arxiv_search/__init__.py
arxiv_search/categories.py
arxiv_search/client.py
arxiv_search/models.py
arxiv_search-0.1.0.dist-info/licenses/LICENSE
arxiv_search-0.1.0.dist-info/METADATA
arxiv_search-0.1.0.dist-info/WHEEL
arxiv_search-0.1.0.dist-info/top_level.txt
arxiv_search-0.1.0.dist-info/RECORD
