Metadata-Version: 2.4
Name: arxiv-search
Version: 0.1.0
Summary: Add your description here
Home-page: https://github.com/li-xiu-qi/arxiv-search-sdk
Author: li-xiu-qi
Author-email: lixiuqixiaoke@qq.com
Requires-Python: >=3.8
License-File: LICENSE
Requires-Dist: aiohttp>=3.8.0
Requires-Dist: feedparser>=6.0.0
Requires-Dist: pydantic>=2.0.0
Requires-Dist: pydantic-settings>=2.0.0
Requires-Dist: python-dotenv>=1.0.0
Requires-Dist: loguru>=0.7.0
Requires-Dist: click>=8.0.0
Requires-Dist: build>=1.0.0
Requires-Dist: twine>=4.0.0
Dynamic: author
Dynamic: author-email
Dynamic: home-page
Dynamic: license-file
Dynamic: requires-python
